{
  "title": "Утренний чек-лист",
  "questions": [
    {
      "id": 1,
      "question": "Прибрать стойку. В том числе, место для сумок.",
      "answers": [
        "Было чисто",
        "Протер(ла) пыль",
        "Убрал(а) мусор"
      ],
      "generalQuestion": "На стойке: "
    },
    {
      "id": 2,
      "question": "Прибрать скамейку. Если есть пыль, иная грязь – протереть.",
      "answers": [
        "Было чисто",
        "Протер(ла) пыль",
        "Убрал(а) мусор"
      ],
      "generalQuestion": "На скамейке: "
    },
    {
      "id": 3,
      "question": "Прибрать стол для клиентов. Если есть пыль, иная грязь – протереть.",
      "answers": [
        "Было чисто",
        "Протер(ла) пыль",
        "Убрал(а) мусор"
      ],
      "generalQuestion": "На столе для клиентов: "
    },
    {
      "id": 4,
      "question": "Запустить слайд шоу на ТВ",
      "answers": [
        "Слайд-шоу запущено"
      ],
      "generalQuestion": "Слайд-шоу запущено"
    },
    {
      "id": 5,
      "question": "Проверить задания по Книге заданий. Подписать неподписанные заказы.",
      "answers": [
        "Неподписанных заказов не было",
        "Заказы подписал(а)"
      ],
      "generalQuestion": "По книге заданий: "
    },
    {
      "id": 6,
      "question": "Проверить наличие расходки. Написать ответственному за доставку, что привезти.",
      "answers": [
        "Заказ расходки не требуется",
        "Требуется поставка, заказал(а)"
      ],
      "generalQuestion": "По наличию расходки: "
    },
    {
      "id": 7,
      "question": "Проверить оплаты к заказам на почте. Если есть, внести в книгу заданий.",
      "answers": [
        "Необработанных оплат не было",
        "Внес(ла) оплаты в книгу заданий"
      ],
      "generalQuestion": "По оплатам: "
    },
    {
      "id": 8,
      "question": "Бейдж. Надеть бейдж на себя, проверить бейдж у коллеги. Если бейджа нет или он в непотребном виде – изготовить.",
      "answers": [
        "Все надели бейдж"
      ],
      "generalQuestion": "Все надели бейдж"
    },
    {
      "id": 9,
      "question": "Проверить работу Telegram и Max. +73433517433 на операторских компьютерах.",
      "answers": [
        "Telegram и Max подключены на все операторские компы"
      ],
      "generalQuestion": "Telegramm и Max: "
    },
    {
      "id": 10,
      "question": "Проверить громкость на телефонах. На всех телефонах должна быть полная громкость.",
      "answers": [
        "Громкость была в норме",
        "Увеличил(а) громкость"
      ],
      "generalQuestion": "Громкость на телефоне: "
    },
    {
      "id": 11,
      "question": "Проверить рекламные материалы на стойке. Визитки, тейбл-тенты, образцы. Если что-то закончилось или в непотребном виде – исправить.",
      "answers": [
        "Материалы в норме",
        "Восполнил(а) визитки",
        "Заменил(а) тейбл-тент"
      ],
      "generalQuestion": "Рекламные материалы на стойке: "
    },
    {
      "id": 12,
      "question": "По вторникам и по пятницам. Полотенца. Собрать все использованные полотенца в корзину. Повесить свежие (2 шт. в туалет).",
      "answers": [
        "Убрал(а) старые полотенца",
        "Повесил(а) новые полотенца",
        "Отдал(а) грязные полотенца в стирку",
        "Полотенца чистые"
      ],
      "generalQuestion": "Полотенца: "
    }
  ]
}